pysankey/__init__.py
pysankey/sankey.py
pysankey/tests/__init__.py
pysankey/tests/generic_test.py
pysankey/tests/test_deprecated.py
pysankey/tests/test_error_case.py
pysankey/tests/test_readme.py
pysankey/tests/test_sankey.py
pySankey2-2.0.1.dist-info/LICENSE
pySankey2-2.0.1.dist-info/METADATA
pySankey2-2.0.1.dist-info/WHEEL
pySankey2-2.0.1.dist-info/top_level.txt
pySankey2-2.0.1.dist-info/RECORD
