Metadata-Version: 2.1
Name: pySankey2
Version: 2.0.1
Summary: Make simple, pretty Sankey Diagrams as a matplotlib object
Home-page: https://github.com/vgalisson/pySankey
Author: victor-galisson
Author-email: victor.galisson@gmail.com
License: GNU General Public License v3.0
Platform: UNKNOWN
Classifier: Programming Language :: Python :: 3.6
Classifier: Programming Language :: Python :: 3.7
Classifier: License :: OSI Approved :: GNU Affero General Public License v3
Classifier: Operating System :: OS Independent
